{
  "framework_version": "bsaf-v1.0",
  "story_id": "36fc311f-20ea-41bf-bd92-a92c719de4d9",
  "title": "[P] Vibecoded on a home PC: building a ~2700 Elo browser-playable neural chess engine with a Karpathy-inspired AI-assisted research loop",
  "source_url": "https://www.reddit.com/r/MachineLearning/comments/1rzrs17/p_vibecoded_on_a_home_pc_building_a_2700_elo/",
  "bs_score": 4.5,
  "bs_rating": "Mixed Signals",
  "category": "community",
  "summary": "Real technical work with specific architecture details, but the ~2700 Elo claim on a 16M param model with 1-ply search is suspiciously strong and conveniently unverified against standardized benchmarks. The 'vibecoded' framing is peak 2026 clout-bait wrapping what's actually a solid hobby project.",
  "editorial_comment": "",
  "scored_at": "2026-03-25T10:33:24.024869+00:00"
}